catgpt/__init__.py
catgpt/model.py
catgpt-0.0.12.dist-info/METADATA
catgpt-0.0.12.dist-info/WHEEL
catgpt-0.0.12.dist-info/RECORD
