Metadata-Version: 2.1
Name: catgpt
Version: 0.0.12
Summary: A simple cli tool to generate text using GPT-turbo
Author: tom
Author-email: tom@gmail.com
Requires-Python: >=3.8,<4.0
Classifier: Programming Language :: Python :: 3
Classifier: Programming Language :: Python :: 3.8
Classifier: Programming Language :: Python :: 3.9
Classifier: Programming Language :: Python :: 3.10
Classifier: Programming Language :: Python :: 3.11
Requires-Dist: codefast (>=23.4.18)
Requires-Dist: python-dotenv (>=1.0.0)
Requires-Dist: sseclient-py (>=1.7.2)
